meta_tooling_protocol-0.1.2.dist-info/licenses/LICENSE
mtp/__init__.py
mtp/api.py
mtp/help.py
mtp/langchain.py
mtp/mcp_server.py
mtp/pydantic_adapter.py
mtp/cli/__init__.py
mtp/cli/app.py
mtp/cli/infra.py
mtp/cli/utils.py
mtp/core/__init__.py
mtp/core/docgen.py
mtp/core/io.py
mtp/core/mcp_client.py
mtp/core/mcp_registry.py
mtp/core/python_tools.py
mtp/core/registry.py
mtp/core/runtime.py
mtp/core/venv.py
mtp/core/infra/__init__.py
mtp/core/infra/cmd.py
mtp/core/infra/mcp.py
mtp/core/infra/openapi.py
mtp/core/infra/python.py
mtp/core/infra/registry.py
meta_tooling_protocol-0.1.2.dist-info/METADATA
meta_tooling_protocol-0.1.2.dist-info/WHEEL
meta_tooling_protocol-0.1.2.dist-info/entry_points.txt
meta_tooling_protocol-0.1.2.dist-info/top_level.txt
meta_tooling_protocol-0.1.2.dist-info/RECORD
