Metadata-Version: 2.4
Name: meta-tooling-protocol
Version: 0.1.2
Summary: Lightweight Python runtime for Meta Tooling Protocol (MTP)
Author: APG Team
License: MIT
Keywords: mtp,tooling,mcp,openapi,sdk
Classifier: Development Status :: 3 - Alpha
Classifier: Intended Audience :: Developers
Classifier: Programming Language :: Python :: 3
Classifier: Programming Language :: Python :: 3.11
Classifier: Programming Language :: Python :: 3.12
Requires-Python: >=3.11
License-File: LICENSE
Requires-Dist: pydantic>=2.0.0
Requires-Dist: httpx>=0.25.0
Requires-Dist: pyyaml>=6.0
Requires-Dist: rich>=13.0.0
Requires-Dist: typer>=0.9.0
Requires-Dist: IPython>=8.0.0
Requires-Dist: nbformat>=5.0.0
Requires-Dist: docstring-parser>=0.15
Provides-Extra: api
Requires-Dist: fastapi>=0.110.0; extra == "api"
Requires-Dist: uvicorn>=0.30.0; extra == "api"
Provides-Extra: langchain
Requires-Dist: langchain-core>=0.2.0; extra == "langchain"
Provides-Extra: mcp
Requires-Dist: fastmcp>=2.0.0; extra == "mcp"
Requires-Dist: mcp>=1.25.0; extra == "mcp"
Provides-Extra: all
Requires-Dist: fastapi>=0.110.0; extra == "all"
Requires-Dist: uvicorn>=0.30.0; extra == "all"
Requires-Dist: langchain-core>=0.2.0; extra == "all"
Requires-Dist: fastmcp>=2.0.0; extra == "all"
Requires-Dist: mcp>=1.25.0; extra == "all"
Dynamic: license-file
